{"CTY":"60590762084","COUNTY":"Orange","MPO":"SCAG","LANDAREA":216586,"DENSITY":0,"EMPDEN":0,"SUBURBANAREA":0,"SUBURBANPOP":0,"PDAAREA":1,"PDAPOP":1,"CDD":1193,"HDD":2200,"PEOPLE":775,"WORKERS":0.74,"WORKCNT":1.28,"HOUSEHOLDS":272,"HHSIZE":2.85,"SIZEOWN":2.02,"SIZERENT":3.38,"GRAD":0.0006,"INCOME2013":64432,"INCOME2007":57344,"AGE":50,"WHITE":0.0081,"LATINO":0.31,"BLACK":0.0006,"ASIAN":0,"OTHERACE":0.0013,"VEHICLES":1.43,"CARCOMMUTE":0.0081,"TIMETOWORK":23.8,"OWN":0.0039,"ROOMS":4.2,"GAS":0.0071,"ELECTRIC":0.0027,"OIL":0,"NOFUEL":0.0002,"OTHERFUEL":0,"YEARBUILT":1973,"SINGDET":0.003,"SQFT":1629,"Children":1.09,"Adults":1.76,"NumPubTrans":65,"Public Transit Commuters":0,"Bus Commuters":0,"Subway Commuters":0,"Railroad Commuters":0,"CITY":"ORANGE"}