{"CTY":"60552014031","COUNTY":"Napa","MPO":"MTC","LANDAREA":148431099,"DENSITY":0,"EMPDEN":0,"SUBURBANAREA":0,"SUBURBANPOP":0,"PDAAREA":0,"PDAPOP":0,"CDD":1193,"HDD":2200,"PEOPLE":427,"WORKERS":0.92,"WORKCNT":1.71,"HOUSEHOLDS":135,"HHSIZE":3.16,"SIZEOWN":2.85,"SIZERENT":4.03,"GRAD":0.0013,"INCOME2013":135982,"INCOME2007":121024,"AGE":58,"WHITE":0.01,"LATINO":0.23,"BLACK":0,"ASIAN":0,"OTHERACE":0,"VEHICLES":2.56,"CARCOMMUTE":0.0074,"TIMETOWORK":53,"OWN":0.0074,"ROOMS":6.4,"GAS":0.0013,"ELECTRIC":0.0018,"OIL":0,"NOFUEL":0,"OTHERFUEL":0.007,"YEARBUILT":1966,"SINGDET":0.0088,"SQFT":1548,"Children":0.93,"Adults":2.23,"NumPubTrans":60,"Public Transit Commuters":14,"Bus Commuters":14,"Subway Commuters":0,"Railroad Commuters":0,"CITY":"NAPA"}