{"CTY":"60530001022","COUNTY":"Monterey","MPO":"Other","LANDAREA":856708,"DENSITY":0,"EMPDEN":0,"SUBURBANAREA":1,"SUBURBANPOP":1,"PDAAREA":0,"PDAPOP":0,"CDD":1193,"HDD":2200,"PEOPLE":4026,"WORKERS":0.7,"WORKCNT":1.92,"HOUSEHOLDS":913,"HHSIZE":4.41,"SIZEOWN":3.91,"SIZERENT":4.91,"GRAD":0.001,"INCOME2013":79212,"INCOME2007":70499,"AGE":45,"WHITE":0.0061,"LATINO":0.65,"BLACK":0.0004,"ASIAN":0.0018,"OTHERACE":0.0018,"VEHICLES":2.31,"CARCOMMUTE":0.0089,"TIMETOWORK":28.4,"OWN":0.005,"ROOMS":5.9,"GAS":0.007,"ELECTRIC":0.0018,"OIL":0,"NOFUEL":0.001,"OTHERFUEL":0.0003,"YEARBUILT":1997,"SINGDET":0.0083,"SQFT":1516,"Children":1.65,"Adults":2.76,"NumPubTrans":200,"Public Transit Commuters":0,"Bus Commuters":0,"Subway Commuters":0,"Railroad Commuters":0,"CITY":"SALINAS"}