{"CTY":"60750168022","COUNTY":"San Francisco","MPO":"MTC","LANDAREA":76918,"DENSITY":0,"EMPDEN":0,"SUBURBANAREA":0,"SUBURBANPOP":0,"PDAAREA":1,"PDAPOP":1,"CDD":1193,"HDD":2200,"PEOPLE":1550,"WORKERS":0.82,"WORKCNT":1.71,"HOUSEHOLDS":668,"HHSIZE":2.32,"SIZEOWN":2.5,"SIZERENT":2.28,"GRAD":0.0023,"INCOME2013":45682,"INCOME2007":40657,"AGE":48,"WHITE":0.0057,"LATINO":0.06,"BLACK":0.0035,"ASIAN":0.0006,"OTHERACE":0.0002,"VEHICLES":1.31,"CARCOMMUTE":0.0051,"TIMETOWORK":29.6,"OWN":0.0018,"ROOMS":3.3,"GAS":0.0041,"ELECTRIC":0.0052,"OIL":0,"NOFUEL":0.0001,"OTHERFUEL":0.0006,"YEARBUILT":1939,"SINGDET":0.0012,"SQFT":773,"Children":0.22,"Adults":2.1,"NumPubTrans":559,"Public Transit Commuters":218,"Bus Commuters":139,"Subway Commuters":79,"Railroad Commuters":0,"CITY":"SAN FRANCISCO"}