{"CTY":"60590633011","COUNTY":"Orange","MPO":"SCAG","LANDAREA":330592,"DENSITY":0,"EMPDEN":0,"SUBURBANAREA":0,"SUBURBANPOP":0,"PDAAREA":1,"PDAPOP":1,"CDD":1193,"HDD":2200,"PEOPLE":1058,"WORKERS":0.86,"WORKCNT":1.44,"HOUSEHOLDS":537,"HHSIZE":1.97,"SIZEOWN":2.11,"SIZERENT":1.94,"GRAD":0.0014,"INCOME2013":57083,"INCOME2007":50804,"AGE":41,"WHITE":0.0092,"LATINO":0.22,"BLACK":0,"ASIAN":0,"OTHERACE":0.0008,"VEHICLES":1.81,"CARCOMMUTE":0.0086,"TIMETOWORK":22.3,"OWN":0.002,"ROOMS":4,"GAS":0.0062,"ELECTRIC":0.0026,"OIL":0,"NOFUEL":0.001,"OTHERFUEL":0.0002,"YEARBUILT":1971,"SINGDET":0.0022,"SQFT":1411,"Children":0.21,"Adults":1.76,"NumPubTrans":110,"Public Transit Commuters":12,"Bus Commuters":12,"Subway Commuters":0,"Railroad Commuters":0,"CITY":"COSTA MESA"}