{"CTY":"60670081311","COUNTY":"Sacramento","MPO":"SACOG","LANDAREA":736700,"DENSITY":0,"EMPDEN":0,"SUBURBANAREA":0,"SUBURBANPOP":0,"PDAAREA":0,"PDAPOP":0,"CDD":1193,"HDD":2200,"PEOPLE":867,"WORKERS":0.86,"WORKCNT":1.61,"HOUSEHOLDS":312,"HHSIZE":2.78,"SIZEOWN":3.49,"SIZERENT":2.23,"GRAD":0.0004,"INCOME2013":86429,"INCOME2007":76922,"AGE":44,"WHITE":0.009,"LATINO":0.06,"BLACK":0.0004,"ASIAN":0,"OTHERACE":0.0006,"VEHICLES":2.04,"CARCOMMUTE":0.0088,"TIMETOWORK":21.5,"OWN":0.0044,"ROOMS":4.5,"GAS":0.0043,"ELECTRIC":0.0052,"OIL":0,"NOFUEL":0.0005,"OTHERFUEL":0,"YEARBUILT":1984,"SINGDET":0.0037,"SQFT":1365,"Children":0.73,"Adults":2.05,"NumPubTrans":61,"Public Transit Commuters":0,"Bus Commuters":0,"Subway Commuters":0,"Railroad Commuters":0,"CITY":"CITRUS HEIGHTS"}