{"CTY":"60670081271","COUNTY":"Sacramento","MPO":"SACOG","LANDAREA":1446219,"DENSITY":0,"EMPDEN":0,"SUBURBANAREA":0,"SUBURBANPOP":0,"PDAAREA":0,"PDAPOP":0,"CDD":1193,"HDD":2200,"PEOPLE":2049,"WORKERS":0.64,"WORKCNT":1.12,"HOUSEHOLDS":709,"HHSIZE":2.89,"SIZEOWN":2.4,"SIZERENT":4.02,"GRAD":0.0003,"INCOME2013":61991,"INCOME2007":55172,"AGE":49,"WHITE":0.0079,"LATINO":0.25,"BLACK":0.0003,"ASIAN":0.0005,"OTHERACE":0.0014,"VEHICLES":2.29,"CARCOMMUTE":0.0089,"TIMETOWORK":29.4,"OWN":0.007,"ROOMS":5.4,"GAS":0.005,"ELECTRIC":0.0049,"OIL":0,"NOFUEL":0,"OTHERFUEL":0.0001,"YEARBUILT":1982,"SINGDET":0.01,"SQFT":1365,"Children":0.94,"Adults":1.95,"NumPubTrans":90,"Public Transit Commuters":23,"Bus Commuters":11,"Subway Commuters":0,"Railroad Commuters":12,"CITY":"CITRUS HEIGHTS"}