{"CTY":"60670096364","COUNTY":"Sacramento","MPO":"SACOG","LANDAREA":665514,"DENSITY":0,"EMPDEN":0,"SUBURBANAREA":1,"SUBURBANPOP":1,"PDAAREA":0,"PDAPOP":0,"CDD":1193,"HDD":2200,"PEOPLE":1701,"WORKERS":0.66,"WORKCNT":1.65,"HOUSEHOLDS":421,"HHSIZE":4.04,"SIZEOWN":3.94,"SIZERENT":5.82,"GRAD":0.0009,"INCOME2013":85889,"INCOME2007":76441,"AGE":48,"WHITE":0.0041,"LATINO":0.13,"BLACK":0.0008,"ASIAN":0.0047,"OTHERACE":0.0004,"VEHICLES":2.24,"CARCOMMUTE":0.0088,"TIMETOWORK":41,"OWN":0.0095,"ROOMS":7.4,"GAS":0.0083,"ELECTRIC":0.0017,"OIL":0,"NOFUEL":0,"OTHERFUEL":0,"YEARBUILT":2004,"SINGDET":0.0098,"SQFT":2289,"Children":0.99,"Adults":3.05,"NumPubTrans":80,"Public Transit Commuters":18,"Bus Commuters":18,"Subway Commuters":0,"Railroad Commuters":0,"CITY":"ELK GROVE"}