{"CTY":"60376703243","COUNTY":"Los Angeles","MPO":"SCAG","LANDAREA":1681020,"DENSITY":0,"EMPDEN":0,"SUBURBANAREA":1,"SUBURBANPOP":1,"PDAAREA":0,"PDAPOP":0,"CDD":1193,"HDD":2200,"PEOPLE":1511,"WORKERS":0.63,"WORKCNT":1.03,"HOUSEHOLDS":514,"HHSIZE":2.94,"SIZEOWN":2.95,"SIZERENT":2,"GRAD":0.0042,"INCOME2013":165473,"INCOME2007":147271,"AGE":67,"WHITE":0.0079,"LATINO":0.02,"BLACK":0.0003,"ASIAN":0.0018,"OTHERACE":0,"VEHICLES":2.6,"CARCOMMUTE":0.0079,"TIMETOWORK":47.6,"OWN":0.0099,"ROOMS":9,"GAS":0.0087,"ELECTRIC":0.0013,"OIL":0,"NOFUEL":0,"OTHERFUEL":0,"YEARBUILT":1959,"SINGDET":0.01,"SQFT":2331,"Children":0.53,"Adults":2.41,"NumPubTrans":113,"Public Transit Commuters":0,"Bus Commuters":0,"Subway Commuters":0,"Railroad Commuters":0,"CITY":"PALOS VERDES PENINSULA"}