{"CTY":"60650432653","COUNTY":"Riverside","MPO":"SCAG","LANDAREA":2043360,"DENSITY":0,"EMPDEN":0,"SUBURBANAREA":0,"SUBURBANPOP":0,"PDAAREA":0,"PDAPOP":0,"CDD":1193,"HDD":2200,"PEOPLE":833,"WORKERS":0.72,"WORKCNT":1.26,"HOUSEHOLDS":312,"HHSIZE":2.67,"SIZEOWN":2.56,"SIZERENT":2.92,"GRAD":0.0003,"INCOME2013":62083,"INCOME2007":55254,"AGE":49,"WHITE":0.0088,"LATINO":0.2,"BLACK":0,"ASIAN":0.0007,"OTHERACE":0.0005,"VEHICLES":2.02,"CARCOMMUTE":0.0092,"TIMETOWORK":28.5,"OWN":0.0068,"ROOMS":6,"GAS":0.0075,"ELECTRIC":0.0025,"OIL":0,"NOFUEL":0,"OTHERFUEL":0,"YEARBUILT":2003,"SINGDET":0.01,"SQFT":2240,"Children":0.66,"Adults":2.01,"NumPubTrans":32,"Public Transit Commuters":19,"Bus Commuters":0,"Subway Commuters":0,"Railroad Commuters":0,"CITY":"TEMECULA"}