{"CTY":"60377017023","COUNTY":"Los Angeles","MPO":"SCAG","LANDAREA":201006,"DENSITY":0,"EMPDEN":0,"SUBURBANAREA":0,"SUBURBANPOP":0,"PDAAREA":1,"PDAPOP":1,"CDD":1193,"HDD":2200,"PEOPLE":1340,"WORKERS":0.96,"WORKCNT":1.44,"HOUSEHOLDS":757,"HHSIZE":1.77,"SIZEOWN":2.14,"SIZERENT":1.76,"GRAD":0.0004,"INCOME2013":65320,"INCOME2007":58135,"AGE":45,"WHITE":0.0088,"LATINO":0.18,"BLACK":0.0001,"ASIAN":0.0003,"OTHERACE":0.0008,"VEHICLES":1.33,"CARCOMMUTE":0.0069,"TIMETOWORK":27.7,"OWN":0.0003,"ROOMS":3.6,"GAS":0.0062,"ELECTRIC":0.0031,"OIL":0,"NOFUEL":0.0006,"OTHERFUEL":0.0001,"YEARBUILT":1962,"SINGDET":0.0006,"SQFT":1620,"Children":0.12,"Adults":1.65,"NumPubTrans":338,"Public Transit Commuters":29,"Bus Commuters":29,"Subway Commuters":0,"Railroad Commuters":0,"CITY":"SANTA MONICA"}