{"CTY":"60670065003","COUNTY":"Sacramento","MPO":"SACOG","LANDAREA":313038,"DENSITY":0,"EMPDEN":0,"SUBURBANAREA":0,"SUBURBANPOP":0,"PDAAREA":1,"PDAPOP":1,"CDD":1193,"HDD":2200,"PEOPLE":1307,"WORKERS":0.39,"WORKCNT":0.63,"HOUSEHOLDS":465,"HHSIZE":2.81,"SIZEOWN":3.7,"SIZERENT":2.12,"GRAD":0.0005,"INCOME2013":16042,"INCOME2007":14277,"AGE":52,"WHITE":0.0027,"LATINO":0.28,"BLACK":0.0052,"ASIAN":0.0006,"OTHERACE":0.0014,"VEHICLES":1.2,"CARCOMMUTE":0.0096,"TIMETOWORK":37.6,"OWN":0.0043,"ROOMS":4.8,"GAS":0.0032,"ELECTRIC":0.0063,"OIL":0,"NOFUEL":0.0002,"OTHERFUEL":0.0003,"YEARBUILT":1964,"SINGDET":0.0055,"SQFT":1193,"Children":1.01,"Adults":1.8,"NumPubTrans":11,"Public Transit Commuters":0,"Bus Commuters":0,"Subway Commuters":0,"Railroad Commuters":0,"CITY":"SACRAMENTO"}