{"CTY":"60670075015","COUNTY":"Sacramento","MPO":"SACOG","LANDAREA":738070,"DENSITY":0,"EMPDEN":0,"SUBURBANAREA":0,"SUBURBANPOP":0,"PDAAREA":1,"PDAPOP":1,"CDD":1193,"HDD":2200,"PEOPLE":1441,"WORKERS":0.65,"WORKCNT":1.15,"HOUSEHOLDS":548,"HHSIZE":2.63,"SIZEOWN":2.19,"SIZERENT":2.67,"GRAD":0.0002,"INCOME2013":34095,"INCOME2007":30345,"AGE":44,"WHITE":0.0059,"LATINO":0.3,"BLACK":0.0016,"ASIAN":0.0007,"OTHERACE":0.0018,"VEHICLES":1.24,"CARCOMMUTE":0.0083,"TIMETOWORK":30.5,"OWN":0.0008,"ROOMS":4.6,"GAS":0.0055,"ELECTRIC":0.0044,"OIL":0,"NOFUEL":0,"OTHERFUEL":0.0001,"YEARBUILT":1981,"SINGDET":0.0018,"SQFT":1347,"Children":0.72,"Adults":1.91,"NumPubTrans":109,"Public Transit Commuters":16,"Bus Commuters":16,"Subway Commuters":0,"Railroad Commuters":0,"CITY":"SACRAMENTO"}