{"CTY":"60190061005","COUNTY":"Fresno","MPO":"San Joaquin Valley","LANDAREA":8500461,"DENSITY":0,"EMPDEN":0,"SUBURBANAREA":1,"SUBURBANPOP":1,"PDAAREA":0,"PDAPOP":0,"CDD":1193,"HDD":2200,"PEOPLE":3071,"WORKERS":0.8,"WORKCNT":2.3,"HOUSEHOLDS":726,"HHSIZE":4.23,"SIZEOWN":4.02,"SIZERENT":4.8,"GRAD":0.0005,"INCOME2013":68000,"INCOME2007":60520,"AGE":44,"WHITE":0.0059,"LATINO":0.72,"BLACK":0.0011,"ASIAN":0,"OTHERACE":0.003,"VEHICLES":2.59,"CARCOMMUTE":0.0085,"TIMETOWORK":25.7,"OWN":0.0073,"ROOMS":6,"GAS":0.0073,"ELECTRIC":0.0019,"OIL":0,"NOFUEL":0.0002,"OTHERFUEL":0.0006,"YEARBUILT":2004,"SINGDET":0.0084,"SQFT":1786,"Children":1.45,"Adults":2.78,"NumPubTrans":256,"Public Transit Commuters":0,"Bus Commuters":0,"Subway Commuters":0,"Railroad Commuters":0,"CITY":"SANGER"}