{"CTY":"60190057043","COUNTY":"Fresno","MPO":"San Joaquin Valley","LANDAREA":639142,"DENSITY":0,"EMPDEN":0,"SUBURBANAREA":0,"SUBURBANPOP":0,"PDAAREA":0,"PDAPOP":0,"CDD":1193,"HDD":2200,"PEOPLE":1219,"WORKERS":0.83,"WORKCNT":1.39,"HOUSEHOLDS":445,"HHSIZE":2.74,"SIZEOWN":2.58,"SIZERENT":3.06,"GRAD":0.0002,"INCOME2013":60057,"INCOME2007":53451,"AGE":53,"WHITE":0.0082,"LATINO":0.26,"BLACK":0,"ASIAN":0.001,"OTHERACE":0.0008,"VEHICLES":1.78,"CARCOMMUTE":0.0096,"TIMETOWORK":19.4,"OWN":0.0068,"ROOMS":5.8,"GAS":0.0057,"ELECTRIC":0.0041,"OIL":0,"NOFUEL":0,"OTHERFUEL":0.0002,"YEARBUILT":1976,"SINGDET":0.0092,"SQFT":1906,"Children":0.7,"Adults":2.04,"NumPubTrans":22,"Public Transit Commuters":0,"Bus Commuters":0,"Subway Commuters":0,"Railroad Commuters":0,"CITY":"CLOVIS"}