{"CTY":"61090011003","COUNTY":"Tuolumne","MPO":"Other","LANDAREA":4391748,"DENSITY":0,"EMPDEN":0,"SUBURBANAREA":0,"SUBURBANPOP":0,"PDAAREA":1,"PDAPOP":1,"CDD":1193,"HDD":2200,"PEOPLE":1581,"WORKERS":0.6,"WORKCNT":0.8,"HOUSEHOLDS":753,"HHSIZE":2.1,"SIZEOWN":1.85,"SIZERENT":2.29,"GRAD":0.0009,"INCOME2013":42153,"INCOME2007":37516,"AGE":55,"WHITE":0.0083,"LATINO":0.04,"BLACK":0.0012,"ASIAN":0.0001,"OTHERACE":0.0005,"VEHICLES":1.57,"CARCOMMUTE":0.0084,"TIMETOWORK":30.5,"OWN":0.0043,"ROOMS":4.7,"GAS":0.0027,"ELECTRIC":0.0025,"OIL":0.0002,"NOFUEL":0,"OTHERFUEL":0.0046,"YEARBUILT":1973,"SINGDET":0.0065,"SQFT":1543,"Children":0.36,"Adults":1.74,"NumPubTrans":96,"Public Transit Commuters":8,"Bus Commuters":8,"Subway Commuters":0,"Railroad Commuters":0,"CITY":"SONORA"}