{"CTY":"61110061003","COUNTY":"Ventura","MPO":"SCAG","LANDAREA":91953,"DENSITY":0,"EMPDEN":0,"SUBURBANAREA":0,"SUBURBANPOP":0,"PDAAREA":0,"PDAPOP":0,"CDD":1193,"HDD":2200,"PEOPLE":2032,"WORKERS":0.69,"WORKCNT":1.53,"HOUSEHOLDS":477,"HHSIZE":4.26,"SIZEOWN":3.06,"SIZERENT":4.84,"GRAD":0.0005,"INCOME2013":34069,"INCOME2007":30321,"AGE":39,"WHITE":0.0038,"LATINO":0.96,"BLACK":0,"ASIAN":0.0003,"OTHERACE":0.0059,"VEHICLES":1.3,"CARCOMMUTE":0.0047,"TIMETOWORK":16.7,"OWN":0.0033,"ROOMS":3.6,"GAS":0.0008,"ELECTRIC":0.0078,"OIL":0,"NOFUEL":0.0014,"OTHERFUEL":0,"YEARBUILT":1983,"SINGDET":0,"SQFT":1999,"Children":2.12,"Adults":2.14,"NumPubTrans":388,"Public Transit Commuters":74,"Bus Commuters":74,"Subway Commuters":0,"Railroad Commuters":0,"CITY":"NEWBURY PARK"}