{"CTY":"60372364003","COUNTY":"Los Angeles","MPO":"SCAG","LANDAREA":458225,"DENSITY":0,"EMPDEN":0,"SUBURBANAREA":0,"SUBURBANPOP":0,"PDAAREA":1,"PDAPOP":1,"CDD":1193,"HDD":2200,"PEOPLE":1376,"WORKERS":0.76,"WORKCNT":1.01,"HOUSEHOLDS":655,"HHSIZE":2.1,"SIZEOWN":1.75,"SIZERENT":2.54,"GRAD":0.0028,"INCOME2013":48264,"INCOME2007":42955,"AGE":55,"WHITE":0.0006,"LATINO":0,"BLACK":0.0087,"ASIAN":0.0002,"OTHERACE":0.0005,"VEHICLES":1.32,"CARCOMMUTE":0.008,"TIMETOWORK":32.8,"OWN":0.0056,"ROOMS":5.1,"GAS":0.0074,"ELECTRIC":0.0022,"OIL":0,"NOFUEL":0.0002,"OTHERFUEL":0.0003,"YEARBUILT":1961,"SINGDET":0.003,"SQFT":1591,"Children":0.52,"Adults":1.58,"NumPubTrans":133,"Public Transit Commuters":35,"Bus Commuters":35,"Subway Commuters":0,"Railroad Commuters":0,"CITY":"LOS ANGELES"}