{"CTY":"60375323022","COUNTY":"Los Angeles","MPO":"SCAG","LANDAREA":2142851,"DENSITY":0,"EMPDEN":0,"SUBURBANAREA":1,"SUBURBANPOP":1,"PDAAREA":0,"PDAPOP":0,"CDD":1193,"HDD":2200,"PEOPLE":1032,"WORKERS":0.58,"WORKCNT":1.82,"HOUSEHOLDS":260,"HHSIZE":3.97,"SIZEOWN":5.44,"SIZERENT":2.98,"GRAD":0.0003,"INCOME2013":32500,"INCOME2007":28925,"AGE":54,"WHITE":0.0087,"LATINO":0.98,"BLACK":0,"ASIAN":0,"OTHERACE":0.0013,"VEHICLES":1.88,"CARCOMMUTE":0.0097,"TIMETOWORK":25.6,"OWN":0.004,"ROOMS":4.6,"GAS":0.0065,"ELECTRIC":0.0007,"OIL":0,"NOFUEL":0.0027,"OTHERFUEL":0,"YEARBUILT":1956,"SINGDET":0.0093,"SQFT":1163,"Children":0.75,"Adults":3.22,"NumPubTrans":15,"Public Transit Commuters":13,"Bus Commuters":13,"Subway Commuters":0,"Railroad Commuters":0,"CITY":"LOS ANGELES"}