{"CTY":"60730049002","COUNTY":"San Diego","MPO":"SANDAG","LANDAREA":247283,"DENSITY":0,"EMPDEN":0,"SUBURBANAREA":0,"SUBURBANPOP":0,"PDAAREA":0,"PDAPOP":0,"CDD":1193,"HDD":2200,"PEOPLE":1451,"WORKERS":0.69,"WORKCNT":1.53,"HOUSEHOLDS":387,"HHSIZE":3.75,"SIZEOWN":2.91,"SIZERENT":3.97,"GRAD":0,"INCOME2013":26950,"INCOME2007":23986,"AGE":51,"WHITE":0.0055,"LATINO":0.9,"BLACK":0.0002,"ASIAN":0,"OTHERACE":0.0043,"VEHICLES":1.19,"CARCOMMUTE":0.0071,"TIMETOWORK":26.3,"OWN":0.0021,"ROOMS":3.8,"GAS":0.0083,"ELECTRIC":0.0013,"OIL":0,"NOFUEL":0,"OTHERFUEL":0.0004,"YEARBUILT":1943,"SINGDET":0.0054,"SQFT":1085,"Children":1.2,"Adults":2.55,"NumPubTrans":171,"Public Transit Commuters":87,"Bus Commuters":87,"Subway Commuters":0,"Railroad Commuters":0,"CITY":"SAN DIEGO"}