{"CTY":"60650427402","COUNTY":"Riverside","MPO":"SCAG","LANDAREA":426922,"DENSITY":0,"EMPDEN":0,"SUBURBANAREA":0,"SUBURBANPOP":0,"PDAAREA":1,"PDAPOP":1,"CDD":1193,"HDD":2200,"PEOPLE":406,"WORKERS":0.12,"WORKCNT":0.05,"HOUSEHOLDS":288,"HHSIZE":1.41,"SIZEOWN":1.36,"SIZERENT":1.78,"GRAD":0.0003,"INCOME2013":23984,"INCOME2007":21346,"AGE":74,"WHITE":0.0098,"LATINO":0.08,"BLACK":0,"ASIAN":0,"OTHERACE":0.0002,"VEHICLES":1.08,"CARCOMMUTE":0.01,"TIMETOWORK":27.6,"OWN":0.0088,"ROOMS":5.3,"GAS":0.0013,"ELECTRIC":0.0087,"OIL":0,"NOFUEL":0,"OTHERFUEL":0,"YEARBUILT":1975,"SINGDET":0.01,"SQFT":1375,"Children":null,"Adults":1.41,"NumPubTrans":null,"Public Transit Commuters":0,"Bus Commuters":0,"Subway Commuters":0,"Railroad Commuters":0,"CITY":"SUN CITY"}