{"CTY":"60650479005","COUNTY":"Riverside","MPO":"SCAG","LANDAREA":1037735,"DENSITY":0,"EMPDEN":0,"SUBURBANAREA":1,"SUBURBANPOP":1,"PDAAREA":0,"PDAPOP":0,"CDD":1193,"HDD":2200,"PEOPLE":2558,"WORKERS":0.82,"WORKCNT":1.91,"HOUSEHOLDS":825,"HHSIZE":3.1,"SIZEOWN":3.22,"SIZERENT":2.24,"GRAD":0.0015,"INCOME2013":99663,"INCOME2007":88700,"AGE":49,"WHITE":0.007,"LATINO":0.25,"BLACK":0,"ASIAN":0.0017,"OTHERACE":0.0013,"VEHICLES":2.36,"CARCOMMUTE":0.0087,"TIMETOWORK":33.8,"OWN":0.0088,"ROOMS":6.9,"GAS":0.0088,"ELECTRIC":0.0012,"OIL":0,"NOFUEL":0,"OTHERFUEL":0,"YEARBUILT":1995,"SINGDET":0.0094,"SQFT":2207,"Children":0.78,"Adults":2.32,"NumPubTrans":200,"Public Transit Commuters":19,"Bus Commuters":0,"Subway Commuters":0,"Railroad Commuters":19,"CITY":"CORONA"}