{"CTY":"60150002024","COUNTY":"Del Norte","MPO":"Other","LANDAREA":1022477315,"DENSITY":0,"EMPDEN":0,"SUBURBANAREA":0,"SUBURBANPOP":0,"PDAAREA":0,"PDAPOP":0,"CDD":1193,"HDD":2200,"PEOPLE":898,"WORKERS":0.79,"WORKCNT":1.21,"HOUSEHOLDS":387,"HHSIZE":2.32,"SIZEOWN":2.25,"SIZERENT":2.54,"GRAD":0.0016,"INCOME2013":66250,"INCOME2007":58963,"AGE":58,"WHITE":0.0089,"LATINO":0.07,"BLACK":0,"ASIAN":0,"OTHERACE":0.0011,"VEHICLES":2.01,"CARCOMMUTE":0.0092,"TIMETOWORK":17.4,"OWN":0.0077,"ROOMS":5.3,"GAS":0.0004,"ELECTRIC":0.0043,"OIL":0.0028,"NOFUEL":0,"OTHERFUEL":0.0024,"YEARBUILT":1977,"SINGDET":0.0078,"SQFT":1610,"Children":0.37,"Adults":1.95,"NumPubTrans":40,"Public Transit Commuters":0,"Bus Commuters":0,"Subway Commuters":0,"Railroad Commuters":0,"CITY":"CRESCENT CITY"}