{"CTY":"60871214033","COUNTY":"Santa Cruz","MPO":"Other","LANDAREA":366753,"DENSITY":0,"EMPDEN":0,"SUBURBANAREA":0,"SUBURBANPOP":0,"PDAAREA":0,"PDAPOP":0,"CDD":1193,"HDD":2200,"PEOPLE":660,"WORKERS":0.61,"WORKCNT":1.41,"HOUSEHOLDS":274,"HHSIZE":2.41,"SIZEOWN":1.91,"SIZERENT":2.78,"GRAD":0.001,"INCOME2013":56615,"INCOME2007":50387,"AGE":54,"WHITE":0.01,"LATINO":0.24,"BLACK":0,"ASIAN":0,"OTHERACE":0,"VEHICLES":1.85,"CARCOMMUTE":0.0076,"TIMETOWORK":31.4,"OWN":0.0043,"ROOMS":3.9,"GAS":0.009,"ELECTRIC":0.001,"OIL":0,"NOFUEL":0,"OTHERFUEL":0,"YEARBUILT":1983,"SINGDET":0.0014,"SQFT":1370,"Children":0.27,"Adults":2.14,"NumPubTrans":92,"Public Transit Commuters":40,"Bus Commuters":40,"Subway Commuters":0,"Railroad Commuters":0,"CITY":"SANTA CRUZ"}