{"CTY":"60371048103","COUNTY":"Los Angeles","MPO":"SCAG","LANDAREA":531329,"DENSITY":0,"EMPDEN":0,"SUBURBANAREA":1,"SUBURBANPOP":1,"PDAAREA":0,"PDAPOP":0,"CDD":1193,"HDD":2200,"PEOPLE":2520,"WORKERS":0.8,"WORKCNT":2.64,"HOUSEHOLDS":524,"HHSIZE":4.81,"SIZEOWN":4.66,"SIZERENT":4.95,"GRAD":0.0002,"INCOME2013":56045,"INCOME2007":49880,"AGE":48,"WHITE":0.0068,"LATINO":0.96,"BLACK":0,"ASIAN":0.0002,"OTHERACE":0.003,"VEHICLES":2.57,"CARCOMMUTE":0.0099,"TIMETOWORK":35,"OWN":0.0049,"ROOMS":5.2,"GAS":0.0064,"ELECTRIC":0.001,"OIL":0,"NOFUEL":0.0026,"OTHERFUEL":0,"YEARBUILT":1957,"SINGDET":0.0098,"SQFT":1323,"Children":1.48,"Adults":3.33,"NumPubTrans":19,"Public Transit Commuters":7,"Bus Commuters":7,"Subway Commuters":0,"Railroad Commuters":0,"CITY":"PACOIMA"}