{"CTY":"60375543012","COUNTY":"Los Angeles","MPO":"SCAG","LANDAREA":269068,"DENSITY":0,"EMPDEN":0,"SUBURBANAREA":0,"SUBURBANPOP":0,"PDAAREA":0,"PDAPOP":0,"CDD":1193,"HDD":2200,"PEOPLE":1350,"WORKERS":0.74,"WORKCNT":1.3,"HOUSEHOLDS":456,"HHSIZE":2.96,"SIZEOWN":3.31,"SIZERENT":2.88,"GRAD":0.0001,"INCOME2013":50917,"INCOME2007":45316,"AGE":43,"WHITE":0.0032,"LATINO":0.46,"BLACK":0.0042,"ASIAN":0,"OTHERACE":0.0027,"VEHICLES":1.32,"CARCOMMUTE":0.0089,"TIMETOWORK":38.4,"OWN":0.002,"ROOMS":3.9,"GAS":0.0075,"ELECTRIC":0.0023,"OIL":0,"NOFUEL":0.0002,"OTHERFUEL":0,"YEARBUILT":1963,"SINGDET":0.0021,"SQFT":1344,"Children":1.05,"Adults":1.91,"NumPubTrans":64,"Public Transit Commuters":50,"Bus Commuters":50,"Subway Commuters":0,"Railroad Commuters":0,"CITY":"BELLFLOWER"}