{"CTY":"60372932022","COUNTY":"Los Angeles","MPO":"SCAG","LANDAREA":249861,"DENSITY":0,"EMPDEN":0,"SUBURBANAREA":1,"SUBURBANPOP":1,"PDAAREA":0,"PDAPOP":0,"CDD":1193,"HDD":2200,"PEOPLE":2476,"WORKERS":0.73,"WORKCNT":2.03,"HOUSEHOLDS":601,"HHSIZE":4.12,"SIZEOWN":4.1,"SIZERENT":4.13,"GRAD":0.0002,"INCOME2013":37227,"INCOME2007":33132,"AGE":45,"WHITE":0.0035,"LATINO":0.73,"BLACK":0.001,"ASIAN":0.0024,"OTHERACE":0.0031,"VEHICLES":1.8,"CARCOMMUTE":0.0083,"TIMETOWORK":28.3,"OWN":0.0018,"ROOMS":4.2,"GAS":0.007,"ELECTRIC":0.0013,"OIL":0,"NOFUEL":0.0015,"OTHERFUEL":0.0001,"YEARBUILT":1968,"SINGDET":0.004,"SQFT":1448,"Children":1.43,"Adults":2.69,"NumPubTrans":204,"Public Transit Commuters":35,"Bus Commuters":35,"Subway Commuters":0,"Railroad Commuters":0,"CITY":"TORRANCE"}