{"CTY":"60375417006","COUNTY":"Los Angeles","MPO":"SCAG","LANDAREA":167256,"DENSITY":0,"EMPDEN":0,"SUBURBANAREA":0,"SUBURBANPOP":0,"PDAAREA":0,"PDAPOP":0,"CDD":1193,"HDD":2200,"PEOPLE":395,"WORKERS":0.81,"WORKCNT":1.82,"HOUSEHOLDS":112,"HHSIZE":3.53,"SIZEOWN":3.38,"SIZERENT":4.57,"GRAD":0,"INCOME2013":66471,"INCOME2007":59159,"AGE":45,"WHITE":0.001,"LATINO":0.87,"BLACK":0.003,"ASIAN":0,"OTHERACE":0.006,"VEHICLES":1.94,"CARCOMMUTE":0.0093,"TIMETOWORK":37.1,"OWN":0.0088,"ROOMS":5.2,"GAS":0.0072,"ELECTRIC":0.0028,"OIL":0,"NOFUEL":0,"OTHERFUEL":0,"YEARBUILT":1939,"SINGDET":0.01,"SQFT":1176,"Children":1.35,"Adults":2.18,"NumPubTrans":14,"Public Transit Commuters":4,"Bus Commuters":0,"Subway Commuters":0,"Railroad Commuters":4,"CITY":"LYNWOOD"}