{"CTY":"60372946202","COUNTY":"Los Angeles","MPO":"SCAG","LANDAREA":226249,"DENSITY":0,"EMPDEN":0,"SUBURBANAREA":0,"SUBURBANPOP":0,"PDAAREA":0,"PDAPOP":0,"CDD":1193,"HDD":2200,"PEOPLE":1832,"WORKERS":0.71,"WORKCNT":1.77,"HOUSEHOLDS":450,"HHSIZE":4.07,"SIZEOWN":3.87,"SIZERENT":4.17,"GRAD":0.0001,"INCOME2013":45278,"INCOME2007":40297,"AGE":50,"WHITE":0.0068,"LATINO":0.94,"BLACK":0.0004,"ASIAN":0,"OTHERACE":0.0028,"VEHICLES":1.24,"CARCOMMUTE":0.0094,"TIMETOWORK":26,"OWN":0.0034,"ROOMS":4.5,"GAS":0.007,"ELECTRIC":0.0021,"OIL":0,"NOFUEL":0.0009,"OTHERFUEL":0,"YEARBUILT":1951,"SINGDET":0.0062,"SQFT":1191,"Children":1.25,"Adults":2.82,"NumPubTrans":51,"Public Transit Commuters":6,"Bus Commuters":6,"Subway Commuters":0,"Railroad Commuters":0,"CITY":"WILMINGTON"}