{"CTY":"60590891071","COUNTY":"Orange","MPO":"SCAG","LANDAREA":804882,"DENSITY":0,"EMPDEN":0,"SUBURBANAREA":1,"SUBURBANPOP":1,"PDAAREA":0,"PDAPOP":0,"CDD":1193,"HDD":2200,"PEOPLE":3135,"WORKERS":0.72,"WORKCNT":2.45,"HOUSEHOLDS":660,"HHSIZE":4.75,"SIZEOWN":4.56,"SIZERENT":5.77,"GRAD":0.0003,"INCOME2013":92924,"INCOME2007":82702,"AGE":53,"WHITE":0.0046,"LATINO":0.54,"BLACK":0,"ASIAN":0.003,"OTHERACE":0.0023,"VEHICLES":2.72,"CARCOMMUTE":0.0099,"TIMETOWORK":27.6,"OWN":0.0084,"ROOMS":6.1,"GAS":0.0068,"ELECTRIC":0.0014,"OIL":0,"NOFUEL":0.0018,"OTHERFUEL":0,"YEARBUILT":1957,"SINGDET":0.01,"SQFT":1495,"Children":1.02,"Adults":3.73,"NumPubTrans":23,"Public Transit Commuters":0,"Bus Commuters":0,"Subway Commuters":0,"Railroad Commuters":0,"CITY":"SANTA ANA"}