{"CTY":"60710042021","COUNTY":"San Bernardino","MPO":"SCAG","LANDAREA":663709,"DENSITY":0,"EMPDEN":0,"SUBURBANAREA":0,"SUBURBANPOP":0,"PDAAREA":0,"PDAPOP":0,"CDD":1193,"HDD":2200,"PEOPLE":2058,"WORKERS":0.61,"WORKCNT":1.13,"HOUSEHOLDS":643,"HHSIZE":3.2,"SIZEOWN":3.45,"SIZERENT":2.91,"GRAD":0.0002,"INCOME2013":27054,"INCOME2007":24078,"AGE":55,"WHITE":0.0042,"LATINO":0.65,"BLACK":0.0034,"ASIAN":0.0001,"OTHERACE":0.0023,"VEHICLES":1.65,"CARCOMMUTE":0.0089,"TIMETOWORK":29.4,"OWN":0.0053,"ROOMS":4.7,"GAS":0.0086,"ELECTRIC":0.0011,"OIL":0,"NOFUEL":0.0004,"OTHERFUEL":0,"YEARBUILT":1953,"SINGDET":0.0089,"SQFT":1084,"Children":0.95,"Adults":2.25,"NumPubTrans":83,"Public Transit Commuters":30,"Bus Commuters":30,"Subway Commuters":0,"Railroad Commuters":0,"CITY":"SAN BERNARDINO"}