{"CTY":"60133820004","COUNTY":"Contra Costa","MPO":"MTC","LANDAREA":572400,"DENSITY":0,"EMPDEN":0,"SUBURBANAREA":0,"SUBURBANPOP":0,"PDAAREA":0,"PDAPOP":0,"CDD":1193,"HDD":2200,"PEOPLE":1952,"WORKERS":0.64,"WORKCNT":1.15,"HOUSEHOLDS":697,"HHSIZE":2.8,"SIZEOWN":3.18,"SIZERENT":2.63,"GRAD":0.0007,"INCOME2013":36178,"INCOME2007":32198,"AGE":48,"WHITE":0.003,"LATINO":0.16,"BLACK":0.0043,"ASIAN":0.002,"OTHERACE":0.0006,"VEHICLES":1.47,"CARCOMMUTE":0.0086,"TIMETOWORK":29.1,"OWN":0.0031,"ROOMS":4,"GAS":0.0062,"ELECTRIC":0.002,"OIL":0,"NOFUEL":0.001,"OTHERFUEL":0.0007,"YEARBUILT":1957,"SINGDET":0.0039,"SQFT":1087,"Children":0.77,"Adults":2.03,"NumPubTrans":116,"Public Transit Commuters":70,"Bus Commuters":40,"Subway Commuters":30,"Railroad Commuters":0,"CITY":"RICHMOND"}