{"CTY":"60133790001","COUNTY":"Contra Costa","MPO":"MTC","LANDAREA":351534,"DENSITY":0,"EMPDEN":0,"SUBURBANAREA":0,"SUBURBANPOP":0,"PDAAREA":0,"PDAPOP":0,"CDD":1193,"HDD":2200,"PEOPLE":1211,"WORKERS":0.66,"WORKCNT":1.29,"HOUSEHOLDS":354,"HHSIZE":3.42,"SIZEOWN":3.46,"SIZERENT":3.4,"GRAD":0.0003,"INCOME2013":39063,"INCOME2007":34766,"AGE":52,"WHITE":0.002,"LATINO":0.5,"BLACK":0.0066,"ASIAN":0,"OTHERACE":0.0013,"VEHICLES":1.45,"CARCOMMUTE":0.007,"TIMETOWORK":34.1,"OWN":0.004,"ROOMS":4.3,"GAS":0.0066,"ELECTRIC":0.0025,"OIL":0,"NOFUEL":0.0003,"OTHERFUEL":0.0006,"YEARBUILT":1955,"SINGDET":0.0066,"SQFT":1087,"Children":1.13,"Adults":2.29,"NumPubTrans":137,"Public Transit Commuters":131,"Bus Commuters":27,"Subway Commuters":104,"Railroad Commuters":0,"CITY":"RICHMOND"}