{"CTY":"61070035023","COUNTY":"Tulare","MPO":"San Joaquin Valley","LANDAREA":1220390,"DENSITY":0,"EMPDEN":0,"SUBURBANAREA":1,"SUBURBANPOP":1,"PDAAREA":0,"PDAPOP":0,"CDD":1193,"HDD":2200,"PEOPLE":2547,"WORKERS":0.63,"WORKCNT":1.22,"HOUSEHOLDS":653,"HHSIZE":3.9,"SIZEOWN":3.08,"SIZERENT":4.89,"GRAD":0,"INCOME2013":44583,"INCOME2007":39679,"AGE":48,"WHITE":0.0081,"LATINO":0.79,"BLACK":0,"ASIAN":0.0002,"OTHERACE":0.0017,"VEHICLES":1.82,"CARCOMMUTE":0.01,"TIMETOWORK":22.5,"OWN":0.0055,"ROOMS":5.9,"GAS":0.0078,"ELECTRIC":0.0016,"OIL":0,"NOFUEL":0.0006,"OTHERFUEL":0,"YEARBUILT":1982,"SINGDET":0.0088,"SQFT":1479,"Children":1.62,"Adults":2.28,"NumPubTrans":2,"Public Transit Commuters":2,"Bus Commuters":2,"Subway Commuters":0,"Railroad Commuters":0,"CITY":"PORTERVILLE"}