{"CTY":"60552016012","COUNTY":"Napa","MPO":"MTC","LANDAREA":3948321,"DENSITY":0,"EMPDEN":0,"SUBURBANAREA":0,"SUBURBANPOP":0,"PDAAREA":1,"PDAPOP":1,"CDD":1193,"HDD":2200,"PEOPLE":1338,"WORKERS":0.83,"WORKCNT":0.96,"HOUSEHOLDS":600,"HHSIZE":2.23,"SIZEOWN":1.86,"SIZERENT":2.35,"GRAD":0.0018,"INCOME2013":61818,"INCOME2007":55018,"AGE":59,"WHITE":0.0087,"LATINO":0.31,"BLACK":0.0005,"ASIAN":0.0002,"OTHERACE":0.0006,"VEHICLES":1.54,"CARCOMMUTE":0.0083,"TIMETOWORK":20,"OWN":0.0026,"ROOMS":4,"GAS":0.0071,"ELECTRIC":0.0021,"OIL":0,"NOFUEL":0,"OTHERFUEL":0.0008,"YEARBUILT":1979,"SINGDET":0.0038,"SQFT":1620,"Children":0.58,"Adults":1.65,"NumPubTrans":99,"Public Transit Commuters":0,"Bus Commuters":0,"Subway Commuters":0,"Railroad Commuters":0,"CITY":"SAINT HELENA"}