{"CTY":"60750215002","COUNTY":"San Francisco","MPO":"MTC","LANDAREA":107526,"DENSITY":0,"EMPDEN":0,"SUBURBANAREA":0,"SUBURBANPOP":0,"PDAAREA":1,"PDAPOP":1,"CDD":1193,"HDD":2200,"PEOPLE":1572,"WORKERS":0.86,"WORKCNT":1.28,"HOUSEHOLDS":806,"HHSIZE":1.95,"SIZEOWN":2.28,"SIZERENT":1.78,"GRAD":0.0037,"INCOME2013":109079,"INCOME2007":97080,"AGE":42,"WHITE":0.0065,"LATINO":0.12,"BLACK":0.001,"ASIAN":0.0022,"OTHERACE":0.0002,"VEHICLES":1.02,"CARCOMMUTE":0.0023,"TIMETOWORK":32,"OWN":0.0034,"ROOMS":4.4,"GAS":0.0076,"ELECTRIC":0.0024,"OIL":0,"NOFUEL":0,"OTHERFUEL":0,"YEARBUILT":1939,"SINGDET":0.0004,"SQFT":1215,"Children":0.38,"Adults":1.57,"NumPubTrans":801,"Public Transit Commuters":539,"Bus Commuters":153,"Subway Commuters":328,"Railroad Commuters":0,"CITY":"SAN FRANCISCO"}